flask_inputs/__init__.py
flask_inputs/inputs.py
flask_inputs/validators.py
flask_inputs2-1.0.0.dist-info/LICENSE.md
flask_inputs2-1.0.0.dist-info/LICENSE.rst
flask_inputs2-1.0.0.dist-info/METADATA
flask_inputs2-1.0.0.dist-info/WHEEL
flask_inputs2-1.0.0.dist-info/top_level.txt
flask_inputs2-1.0.0.dist-info/RECORD
