Metadata-Version: 2.1
Name: flask-inputs2
Version: 1.0.0
Summary: Flask request data validation
Home-page: http://github.com/durera/flask-inputs/
Author: David Parker
Author-email: durera@gmail.com
License: MIT
Keywords: flask validation wtforms
Requires-Python: >=3.9
License-File: LICENSE.md
License-File: LICENSE.rst
Requires-Dist: flask >=3
Requires-Dist: wtforms >=3
Requires-Dist: future >=1
Provides-Extra: dev
Requires-Dist: build ; extra == 'dev'
Requires-Dist: pytest ; extra == 'dev'
Requires-Dist: email-validator ; extra == 'dev'
Requires-Dist: jsonschema ; extra == 'dev'
